satarray/__init__.py
satarray/cli.py
satarray/common.py
satarray/satarray.py
satarray-0.0.1.dist-info/licenses/LICENSE
satarray-0.0.1.dist-info/METADATA
satarray-0.0.1.dist-info/WHEEL
satarray-0.0.1.dist-info/entry_points.txt
satarray-0.0.1.dist-info/top_level.txt
satarray-0.0.1.dist-info/RECORD
